boa_restrictor/__init__.py
boa_restrictor/cli/__init__.py
boa_restrictor/cli/configuration.py
boa_restrictor/cli/main.py
boa_restrictor/cli/utils.py
boa_restrictor/common/__init__.py
boa_restrictor/common/noqa.py
boa_restrictor/common/rule.py
boa_restrictor/exceptions/__init__.py
boa_restrictor/exceptions/configuration.py
boa_restrictor/exceptions/syntax_errors.py
boa_restrictor/projections/__init__.py
boa_restrictor/projections/occurrence.py
boa_restrictor/rules/__init__.py
boa_restrictor/rules/django/__init__.py
boa_restrictor/rules/django/avoid_tuple_based_model_choices.py
boa_restrictor/rules/django/no_assert_booleans_in_tests.py
boa_restrictor/rules/django/no_db_in_api.py
boa_restrictor/rules/django/no_db_in_views.py
boa_restrictor/rules/django/prohibit_assert_raises.py
boa_restrictor/rules/django/prohibit_datetime_now.py
boa_restrictor/rules/python/__init__.py
boa_restrictor/rules/python/abstract_class_inherits_from_abc.py
boa_restrictor/rules/python/asterisk_required.py
boa_restrictor/rules/python/dataclass_kw_only.py
boa_restrictor/rules/python/global_import_datetime.py
boa_restrictor/rules/python/no_loops_in_tests.py
boa_restrictor/rules/python/no_type_hints_in_variable_names.py
boa_restrictor/rules/python/return_type_hints.py
boa_restrictor/rules/python/service_class_only_one_public.py
boa_restrictor-1.12.6.dist-info/METADATA
boa_restrictor-1.12.6.dist-info/WHEEL
boa_restrictor-1.12.6.dist-info/entry_points.txt
boa_restrictor-1.12.6.dist-info/licenses/LICENSE.md
boa_restrictor-1.12.6.dist-info/RECORD
