Metadata-Version: 2.4
Name: boa-restrictor
Version: 1.12.6
Summary: A custom Python and Django linter from Ambient
Project-URL: Homepage, https://github.com/ambient-innovation/boa-restrictor/
Project-URL: Documentation, https://boa-restrictor.readthedocs.io/en/latest/index.html
Project-URL: Maintained by, https://ambient.digital/
Project-URL: Bugtracker, https://github.com/ambient-innovation/boa-restrictor/issues
Project-URL: Changelog, https://boa-restrictor.readthedocs.io/en/latest/features/changelog.html
Author-email: Ambient Digital <hello@ambient.digital>
License: MIT License
License-File: LICENSE.md
Classifier: Development Status :: 4 - Beta
Classifier: Environment :: Web Environment
Classifier: Framework :: Django
Classifier: Framework :: Django :: 4.2
Classifier: Framework :: Django :: 5.2
Classifier: Framework :: Django :: 6.0
Classifier: Intended Audience :: Developers
Classifier: License :: OSI Approved :: MIT License
Classifier: Natural Language :: English
Classifier: Operating System :: OS Independent
Classifier: Programming Language :: Python
Classifier: Programming Language :: Python :: 3
Classifier: Programming Language :: Python :: 3.10
Classifier: Programming Language :: Python :: 3.11
Classifier: Programming Language :: Python :: 3.12
Classifier: Programming Language :: Python :: 3.13
Classifier: Programming Language :: Python :: 3.14
Classifier: Topic :: Utilities
Requires-Python: >=3.10
Requires-Dist: django>=4.2
Requires-Dist: tomli; python_version < '3.11'
Provides-Extra: dev
Requires-Dist: ambient-package-update; extra == 'dev'
Requires-Dist: m2r2~=0.3; extra == 'dev'
Requires-Dist: pre-commit~=4.3; extra == 'dev'
Requires-Dist: pytest-cov~=7.0; extra == 'dev'
Requires-Dist: pytest-django~=4.11; extra == 'dev'
Requires-Dist: pytest-mock~=3.15; extra == 'dev'
Requires-Dist: sphinx-rtd-theme~=3.0; extra == 'dev'
Requires-Dist: sphinx~=7.4; extra == 'dev'
Requires-Dist: typer~=0.19; extra == 'dev'
Requires-Dist: uv~=0.9; extra == 'dev'
